setup.py
csvtools/__init__.py
csvtools/add_id.py
csvtools/concatenate.py
csvtools/csv2tsv.py
csvtools/extract_map.py
csvtools/field.py
csvtools/field_maps.py
csvtools/left_join.py
csvtools/lib.py
csvtools/max.py
csvtools/merge_fields.py
csvtools/pad.py
csvtools/rmfields.py
csvtools/select.py
csvtools/sort.py
csvtools/split.py
csvtools/to_postgres.py
csvtools/transformer.py
csvtools/tsv2csv.py
csvtools/unzip.py
csvtools/zip.py
csvtools.egg-info/PKG-INFO
csvtools.egg-info/SOURCES.txt
csvtools.egg-info/dependency_links.txt
csvtools.egg-info/entry_points.txt
csvtools.egg-info/top_level.txt