Metadata-Version: 1.1
Name: csvtools
Version: 0.5.1
Summary: Tools for transforming .csv files
Home-page: https://github.com/ceumicrodata/csvtools
Author: CEU MicroData
Author-email: UNKNOWN
License: UNKNOWN
Platform: UNKNOWN
Provides: csvtools (0.5.1)
